odoo/addons/base_archive_security/README.rst
odoo/addons/base_archive_security/__init__.py
odoo/addons/base_archive_security/__manifest__.py
odoo/addons/base_archive_security/hooks.py
odoo/addons/base_archive_security/i18n/base_archive_security.pot
odoo/addons/base_archive_security/i18n/es.po
odoo/addons/base_archive_security/i18n/fr.po
odoo/addons/base_archive_security/i18n/it.po
odoo/addons/base_archive_security/i18n/pt_BR.po
odoo/addons/base_archive_security/models/__init__.py
odoo/addons/base_archive_security/models/base.py
odoo/addons/base_archive_security/readme/CONTRIBUTORS.rst
odoo/addons/base_archive_security/readme/DESCRIPTION.rst
odoo/addons/base_archive_security/readme/USAGE.rst
odoo/addons/base_archive_security/security/res_groups.xml
odoo/addons/base_archive_security/static/description/icon.png
odoo/addons/base_archive_security/static/description/index.html
odoo/addons/base_archive_security/static/src/js/form_controller.esm.js
odoo/addons/base_archive_security/static/src/js/list_controller.esm.js
odoo/addons/base_archive_security/tests/__init__.py
odoo/addons/base_archive_security/tests/test_archive_security.py
odoo_addon_base_archive_security-16.0.1.0.1.4.dist-info/METADATA
odoo_addon_base_archive_security-16.0.1.0.1.4.dist-info/WHEEL
odoo_addon_base_archive_security-16.0.1.0.1.4.dist-info/top_level.txt
odoo_addon_base_archive_security-16.0.1.0.1.4.dist-info/RECORD
